{
  "id": 79,
  "title": "A New Settlement in the North",
  "article_text": "My family had the intention to move to a northern settlement. The gap between our old home and the new one was enormous. We wanted to expose ourselves to a rare opportunity for a fresh start. My father was a critic of city life, so he was happy to leave. The minimum we needed was a small house with a sweet garden. After a long struggle, we achieved a victory and found a permanent home. The estate had a dozen trees and was widely known for its beauty. The weather was variable, but we stayed alive and well. We used to argue about everything, but now we resolve our problems quickly. I advise everyone to acknowledge that a simple life can be equally rewarding.",
  "sentences": [
    {
      "en": "My family had the intention to move to a northern settlement.",
      "zh": "我的家人有意搬到北部的一个定居点。",
      "words": [
        {
          "word": "intention",
          "def": "意图；打算",
          "ipa": "/ɪnˈtenʃən/",
          "eng_def": "a plan or purpose to do something"
        },
        {
          "word": "northern",
          "def": "北方的；北部的",
          "ipa": "/ˈnɔːrðərn/",
          "eng_def": "in or from the north part of a place"
        },
        {
          "word": "settlement",
          "def": "定居点；解决",
          "ipa": "/ˈsetlmənt/",
          "eng_def": "a place where people live; an agreement"
        }
      ]
    },
    {
      "en": "The gap between our old home and the new one was enormous.",
      "zh": "我们的旧家和新家之间的差距是巨大的。",
      "words": [
        {
          "word": "gap",
          "def": "差距；间隙",
          "ipa": "/ɡæp/",
          "eng_def": "a space or difference between two things"
        },
        {
          "word": "enormous",
          "def": "巨大的；庞大的",
          "ipa": "/ɪˈnɔːrməs/",
          "eng_def": "very large in size or amount"
        }
      ]
    },
    {
      "en": "We wanted to expose ourselves to a rare opportunity for a fresh start.",
      "zh": "我们想让自己接触一个难得的机会，重新开始。",
      "words": [
        {
          "word": "expose",
          "def": "使接触；暴露",
          "ipa": "/ɪkˈspoʊz/",
          "eng_def": "to show something that is usually hidden; to let someone experience something"
        },
        {
          "word": "rare",
          "def": "稀有的；难得的",
          "ipa": "/rer/",
          "eng_def": "not common; unusual"
        }
      ]
    },
    {
      "en": "My father was a critic of city life, so he was happy to leave.",
      "zh": "我父亲是城市生活的批评者，所以他很高兴离开。",
      "words": [
        {
          "word": "critic",
          "def": "批评者；评论家",
          "ipa": "/ˈkrɪtɪk/",
          "eng_def": "a person who says what is wrong with something or who gives judgments"
        }
      ]
    },
    {
      "en": "The minimum we needed was a small house with a sweet garden.",
      "zh": "我们需要的最低限度是一栋带甜美花园的小房子。",
      "words": [
        {
          "word": "minimum",
          "def": "最小值；最低限度",
          "ipa": "/ˈmɪnɪməm/",
          "eng_def": "the smallest amount or number allowed or possible"
        },
        {
          "word": "sweet",
          "def": "甜的；甜美的",
          "ipa": "/swiːt/",
          "eng_def": "having a taste like sugar; pleasant"
        }
      ]
    },
    {
      "en": "After a long struggle, we achieved a victory and found a permanent home.",
      "zh": "经过长期奋斗，我们取得了胜利，找到了一个永久的家。",
      "words": [
        {
          "word": "victory",
          "def": "胜利",
          "ipa": "/ˈvɪktəri/",
          "eng_def": "the act of winning a fight or competition"
        },
        {
          "word": "permanent",
          "def": "永久的；长期的",
          "ipa": "/ˈpɜːrmənənt/",
          "eng_def": "lasting for a long time or forever"
        },
        {
          "word": "found",
          "def": "[待补充]",
          "ipa": "",
          "eng_def": "Common English word. (definition needs review)"
        }
      ]
    },
    {
      "en": "The estate had a dozen trees and was widely known for its beauty.",
      "zh": "这片庄园有十几棵树，并且因其美丽而广为人知。",
      "words": [
        {
          "word": "estate",
          "def": "庄园；地产",
          "ipa": "/ɪˈsteɪt/",
          "eng_def": "a large area of land with a big house"
        },
        {
          "word": "dozen",
          "def": "一打；十二个",
          "ipa": "/ˈdʌzən/",
          "eng_def": "a group of twelve things"
        },
        {
          "word": "widely",
          "def": "广泛地",
          "ipa": "/ˈwaɪdli/",
          "eng_def": "over a large area; by many people"
        },
        {
          "word": "known",
          "def": "[待补充]",
          "ipa": "",
          "eng_def": "Common English word. (definition needs review)"
        },
        {
          "word": "beauty",
          "def": "[待补充]",
          "ipa": "",
          "eng_def": "Common English word. (definition needs review)"
        }
      ]
    },
    {
      "en": "The weather was variable, but we stayed alive and well.",
      "zh": "天气多变，但我们安然无恙。",
      "words": [
        {
          "word": "variable",
          "def": "变化的；可变的",
          "ipa": "/ˈveriəbl/",
          "eng_def": "likely to change; not constant"
        },
        {
          "word": "alive",
          "def": "活着的；有活力的",
          "ipa": "/əˈlaɪv/",
          "eng_def": "living; not dead"
        }
      ]
    },
    {
      "en": "We used to argue about everything, but now we resolve our problems quickly.",
      "zh": "我们过去事事争吵，但现在我们迅速解决我们的问题。",
      "words": [
        {
          "word": "resolve",
          "def": "解决；决心",
          "ipa": "/rɪˈzɑːlv/",
          "eng_def": "to find a way to deal with a problem"
        }
      ]
    },
    {
      "en": "I advise everyone to acknowledge that a simple life can be equally rewarding.",
      "zh": "我建议每个人都承认，简单的生活同样可以带来回报。",
      "words": [
        {
          "word": "advise",
          "def": "建议；劝告",
          "ipa": "/ədˈvaɪz/",
          "eng_def": "to tell someone what you think they should do"
        },
        {
          "word": "acknowledge",
          "def": "承认；确认",
          "ipa": "/əkˈnɑːlɪdʒ/",
          "eng_def": "to accept or admit that something is true"
        },
        {
          "word": "equally",
          "def": "同样地；平等地",
          "ipa": "/ˈiːkwəli/",
          "eng_def": "in the same way or amount"
        }
      ]
    }
  ],
  "vocabulary": [
    {
      "word": "rare",
      "def": "稀有的；难得的",
      "ipa": "/rer/",
      "eng_def": "not common; unusual",
      "example": "We wanted to expose ourselves to a rare opportunity."
    },
    {
      "word": "intention",
      "def": "意图；打算",
      "ipa": "/ɪnˈtenʃən/",
      "eng_def": "a plan or purpose to do something",
      "example": "My family had the intention to move."
    },
    {
      "word": "dozen",
      "def": "一打；十二个",
      "ipa": "/ˈdʌzən/",
      "eng_def": "a group of twelve things",
      "example": "The estate had a dozen trees."
    },
    {
      "word": "settlement",
      "def": "定居点；解决",
      "ipa": "/ˈsetlmənt/",
      "eng_def": "a place where people live; an agreement",
      "example": "We moved to a northern settlement."
    },
    {
      "word": "gap",
      "def": "差距；间隙",
      "ipa": "/ɡæp/",
      "eng_def": "a space or difference between two things",
      "example": "The gap was enormous."
    },
    {
      "word": "widely",
      "def": "广泛地",
      "ipa": "/ˈwaɪdli/",
      "eng_def": "over a large area; by many people",
      "example": "It was widely known for its beauty."
    },
    {
      "word": "minimum",
      "def": "最小值；最低限度",
      "ipa": "/ˈmɪnɪməm/",
      "eng_def": "the smallest amount or number allowed or possible",
      "example": "The minimum we needed was a small house."
    },
    {
      "word": "northern",
      "def": "北方的；北部的",
      "ipa": "/ˈnɔːrðərn/",
      "eng_def": "in or from the north part of a place",
      "example": "We moved to a northern settlement."
    },
    {
      "word": "estate",
      "def": "庄园；地产",
      "ipa": "/ɪˈsteɪt/",
      "eng_def": "a large area of land with a big house",
      "example": "The estate had a dozen trees."
    },
    {
      "word": "equally",
      "def": "同样地；平等地",
      "ipa": "/ˈiːkwəli/",
      "eng_def": "in the same way or amount",
      "example": "A simple life can be equally rewarding."
    },
    {
      "word": "expose",
      "def": "使接触；暴露",
      "ipa": "/ɪkˈspoʊz/",
      "eng_def": "to show something that is usually hidden; to let someone experience something",
      "example": "We wanted to expose ourselves to a rare opportunity."
    },
    {
      "word": "alive",
      "def": "活着的；有活力的",
      "ipa": "/əˈlaɪv/",
      "eng_def": "living; not dead",
      "example": "We stayed alive and well."
    },
    {
      "word": "shut",
      "def": "关闭",
      "ipa": "/ʃʌt/",
      "eng_def": "to close something",
      "example": "Shut the door quietly."
    },
    {
      "word": "victory",
      "def": "胜利",
      "ipa": "/ˈvɪktəri/",
      "eng_def": "the act of winning a fight or competition",
      "example": "We achieved a victory."
    },
    {
      "word": "resolve",
      "def": "解决；决心",
      "ipa": "/rɪˈzɑːlv/",
      "eng_def": "to find a way to deal with a problem",
      "example": "We resolve our problems quickly."
    },
    {
      "word": "critic",
      "def": "批评者；评论家",
      "ipa": "/ˈkrɪtɪk/ ",
      "eng_def": "a person who says what is wrong with something or who gives judgments",
      "example": "My father was a critic of city life."
    },
    {
      "word": "variable",
      "def": "变化的；可变的",
      "ipa": "/ˈveriəbl/",
      "eng_def": "likely to change; not constant",
      "example": "The weather was variable."
    },
    {
      "word": "enormous",
      "def": "巨大的；庞大的",
      "ipa": "/ɪˈnɔːrməs/",
      "eng_def": "very large in size or amount",
      "example": "The gap was enormous."
    },
    {
      "word": "sweet",
      "def": "甜的；甜美的",
      "ipa": "/swiːt/",
      "eng_def": "having a taste like sugar; pleasant",
      "example": "We wanted a sweet garden."
    },
    {
      "word": "permanent",
      "def": "永久的；长期的",
      "ipa": "/ˈpɜːrmənənt/",
      "eng_def": "lasting for a long time or forever",
      "example": "We found a permanent home."
    }
  ],
  "quiz": [
    {
      "question_cn": "哪个词意思是‘巨大的’？",
      "question_en": "Which word means 'very large'?",
      "options": [
        "A. rare",
        "B. enormous",
        "C. sweet",
        "D. variable"
      ],
      "answer": 1,
      "word": "enormous"
    },
    {
      "question_cn": "哪个词意思是‘解决’？",
      "question_en": "Which word means 'to find a way to deal with a problem'?",
      "options": [
        "A. expose",
        "B. resolve",
        "C. acknowledge",
        "D. advise"
      ],
      "answer": 1,
      "word": "resolve"
    },
    {
      "question_cn": "哪个词意思是‘永久的’？",
      "question_en": "Which word means 'lasting for a long time'?",
      "options": [
        "A. permanent",
        "B. variable",
        "C. northern",
        "D. alive"
      ],
      "answer": 0,
      "word": "permanent"
    },
    {
      "question_cn": "哪个词意思是‘意图’？",
      "question_en": "Which word means 'a plan or purpose'?",
      "options": [
        "A. intention",
        "B. victory",
        "C. gap",
        "D. dozen"
      ],
      "answer": 0,
      "word": "intention"
    },
    {
      "question_cn": "哪个词意思是‘批评者’？",
      "question_en": "Which word means 'a person who gives judgments'?",
      "options": [
        "A. critic",
        "B. settlement",
        "C. estate",
        "D. minimum"
      ],
      "answer": 0,
      "word": "critic"
    }
  ],
  "image_prompts": [
    "A family packing their car, with a map showing a northern destination.",
    "A wide empty space between two houses, showing a big difference.",
    "A person looking at a beautiful sunset over a new land, feeling excited.",
    "A man shaking his head at a noisy city street, then smiling at a quiet country road.",
    "A small cozy house with a colorful flower garden in front.",
    "A family raising their arms in joy in front of a new house with a 'sold' sign.",
    "A large green area with many tall trees and a big house in the background.",
    "A sunny day turning into a stormy sky, with a person standing safely under a roof.",
    "Two people sitting at a table, talking calmly instead of shouting.",
    "A person giving friendly advice to a friend, both smiling in a simple garden."
  ],
  "_validation_errors": [
    "Missing new words in article: ['shut']"
  ],
  "_needs_review": true,
  "_lesson_num": 79,
  "_new_word_count": 20
}